pylint_tensorflow/__init__.py
pylint_tensorflow-0.0.2.dist-info/LICENSE
pylint_tensorflow-0.0.2.dist-info/METADATA
pylint_tensorflow-0.0.2.dist-info/WHEEL
pylint_tensorflow-0.0.2.dist-info/top_level.txt
pylint_tensorflow-0.0.2.dist-info/RECORD
